mqtt_application/__init__.py
mqtt_application/application.py
mqtt_application/command_handler.py
mqtt_application/config.py
mqtt_application/connection_manager.py
mqtt_application/mqtt_client.py
mqtt_application/status_publisher.py
mqtt_application/worker.py
muxu_io_mqtt_application-1.1.0.dist-info/licenses/LICENSE
muxu_io_mqtt_application-1.1.0.dist-info/METADATA
muxu_io_mqtt_application-1.1.0.dist-info/WHEEL
muxu_io_mqtt_application-1.1.0.dist-info/top_level.txt
muxu_io_mqtt_application-1.1.0.dist-info/RECORD
