Metadata-Version: 2.4
Name: muxu-io-mqtt-application
Version: 1.1.0
Summary: A comprehensive asynchronous MQTT application library
Author-email: Alex Gonzalez <alex@muxu.io>
License: MIT
Project-URL: Homepage, https://github.com/muxu-io/mqtt-application
Project-URL: Repository, https://github.com/muxu-io/mqtt-application.git
Project-URL: Issues, https://github.com/muxu-io/mqtt-application/issues
Keywords: mqtt,async,iot,messaging,client
Classifier: Development Status :: 3 - Alpha
Classifier: Intended Audience :: Developers
Classifier: Programming Language :: Python :: 3
Classifier: Programming Language :: Python :: 3.9
Classifier: Programming Language :: Python :: 3.10
Classifier: Programming Language :: Python :: 3.11
Classifier: Topic :: Software Development :: Libraries :: Python Modules
Classifier: Topic :: Communications
Classifier: Topic :: Internet :: WWW/HTTP :: Browsers
Requires-Python: >=3.9
License-File: LICENSE
Requires-Dist: pyyaml>=6.0.0
Requires-Dist: muxu-io-mqtt-logger
Requires-Dist: muxu-io-mqtt-connector
Provides-Extra: dev
Requires-Dist: pytest>=7.0.0; extra == "dev"
Requires-Dist: pytest-asyncio>=0.21.0; extra == "dev"
Requires-Dist: pytest-cov>=4.0.0; extra == "dev"
Requires-Dist: pytest-xdist>=3.0.0; extra == "dev"
Requires-Dist: black>=22.0.0; extra == "dev"
Requires-Dist: mypy>=1.0.0; extra == "dev"
Requires-Dist: ruff>=0.1.0; extra == "dev"
Requires-Dist: bandit[toml]>=1.7.0; extra == "dev"
Requires-Dist: pip-audit>=2.6.0; extra == "dev"
Requires-Dist: build>=0.10.0; extra == "dev"
Requires-Dist: twine>=4.0.0; extra == "dev"
Provides-Extra: testing
Requires-Dist: pytest-watch>=4.2.0; extra == "testing"
Requires-Dist: pytest-sugar>=0.9.0; extra == "testing"
Requires-Dist: pytest-html>=3.1.0; extra == "testing"
Dynamic: license-file
